chakra/__init__.py
chakra/Chakra/AppAnimations.qml
chakra/Chakra/AppStyle.qml
chakra/Chakra/CActionBar.qml
chakra/Chakra/CAlert.qml
chakra/Chakra/CBadge.qml
chakra/Chakra/CBox.qml
chakra/Chakra/CButton.qml
chakra/Chakra/CCard.qml
chakra/Chakra/CCenter.qml
chakra/Chakra/CCheckbox.qml
chakra/Chakra/CContainer.qml
chakra/Chakra/CContentWidthUpdater.qml
chakra/Chakra/CDialog.qml
chakra/Chakra/CDrawer.qml
chakra/Chakra/CFlex.qml
chakra/Chakra/CFlow.qml
chakra/Chakra/CFrameless.py
chakra/Chakra/CGridView.qml
chakra/Chakra/CHoverCard.qml
chakra/Chakra/CIcon.qml
chakra/Chakra/CInput.qml
chakra/Chakra/CListView.qml
chakra/Chakra/CMenu.qml
chakra/Chakra/CMenuGroup.qml
chakra/Chakra/CMenuItem.qml
chakra/Chakra/CMenuSeparator.qml
chakra/Chakra/CPagination.qml
chakra/Chakra/CPopupBase.qml
chakra/Chakra/CPopupCloseButton.qml
chakra/Chakra/CPopupDivider.qml
chakra/Chakra/CProgress.qml
chakra/Chakra/CScrollArea.qml
chakra/Chakra/CScrollBar.qml
chakra/Chakra/CSegmentedControl.qml
chakra/Chakra/CSelect.qml
chakra/Chakra/CSpacer.qml
chakra/Chakra/CSpinner.qml
chakra/Chakra/CSwitch.qml
chakra/Chakra/CTag.qml
chakra/Chakra/CTooltip.qml
chakra/Chakra/CWindow.qml
chakra/Chakra/CWindowButton.qml
chakra/Chakra/CWindowControls.qml
chakra/Chakra/Icons.qml
chakra/Chakra/__init__.py
chakra/Chakra/qmldir
chakra/Chakra/fonts/Phosphor.ttf
chakra_qml-0.1.0.dist-info/licenses/LICENSE
chakra_qml-0.1.0.dist-info/METADATA
chakra_qml-0.1.0.dist-info/WHEEL
chakra_qml-0.1.0.dist-info/top_level.txt
chakra_qml-0.1.0.dist-info/RECORD
